sravniotzyvy_com/__init__.py
sravniotzyvy_com/sravniotzyvy_com.py
sravniotzyvy_com-0.1.5.dist-info/LICENSE
sravniotzyvy_com-0.1.5.dist-info/METADATA
sravniotzyvy_com-0.1.5.dist-info/WHEEL
sravniotzyvy_com-0.1.5.dist-info/top_level.txt
sravniotzyvy_com-0.1.5.dist-info/RECORD
