Metadata-Version: 2.1
Name: sravniotzyvy-com
Version: 0.1.5
Summary: sravniotzyvy_com
Home-page: https://github.com/NMelis/sravniotzyvy_com
Author: Melis Nurlan
Author-email: melis.zhoroev@gmail.com
License: MIT license
Keywords: sravniotzyvy_com
Platform: UNKNOWN
Classifier: Development Status :: 2 - Pre-Alpha
Classifier: Intended Audience :: Developers
Classifier: License :: OSI Approved :: MIT License
Classifier: Natural Language :: English
Classifier: Programming Language :: Python :: 2
Classifier: Programming Language :: Python :: 2.7
Classifier: Programming Language :: Python :: 3
Classifier: Programming Language :: Python :: 3.4
Classifier: Programming Language :: Python :: 3.5
Classifier: Programming Language :: Python :: 3.6
Classifier: Programming Language :: Python :: 3.7
Requires-Dist: requests
Requires-Dist: bs4
